palantir_oauth_client/__init__.py
palantir_oauth_client/_client.py
palantir_oauth_client/_flow.py
palantir_oauth_client/_utils.py
palantir_oauth_client/_webserver.py
palantir_oauth_client/auth.py
palantir_oauth_client/cache.py
palantir_oauth_client/credentials.py
palantir_oauth_client/errors.py
palantir_oath_client-1.5.0.dist-info/LICENSE
palantir_oath_client-1.5.0.dist-info/WHEEL
palantir_oath_client-1.5.0.dist-info/METADATA
palantir_oath_client-1.5.0.dist-info/RECORD
