Metadata-Version: 2.1
Name: palantir-oath-client
Version: 1.5.0
Summary: OAuth2 client for Palantir Foundry
Home-page: https://github.com/palantir/palantir-oauth-client
Author: Thomas Powell
Author-email: tpowell@palantir.com
Requires-Python: >=3.9,<4.0
Classifier: Programming Language :: Python :: 3
Classifier: Programming Language :: Python :: 3.10
Classifier: Programming Language :: Python :: 3.9
Requires-Dist: oauthlib (>=3.2.2,<4.0.0)
Requires-Dist: requests (>=2.28.2,<3.0.0)
Requires-Dist: requests-oauthlib (>=1.3.1,<2.0.0)
Requires-Dist: typing (>=3.7.4,<4.0.0)
Requires-Dist: urllib3 (>=1.26.14,<2.0.0)
